datus_semantic_metricflow/__init__.py
datus_semantic_metricflow/adapter.py
datus_semantic_metricflow/config.py
datus_semantic_metricflow/models.py
datus_semantic_metricflow/examples/basic_usage.py
datus_semantic_metricflow/tests/__init__.py
datus_semantic_metricflow/tests/test_adapter.py
datus_semantic_metricflow/tests/test_registry.py
datus_semantic_metricflow-0.1.2.dist-info/METADATA
datus_semantic_metricflow-0.1.2.dist-info/WHEEL
datus_semantic_metricflow-0.1.2.dist-info/entry_points.txt
datus_semantic_metricflow-0.1.2.dist-info/top_level.txt
datus_semantic_metricflow-0.1.2.dist-info/RECORD
