Metadata-Version: 2.4
Name: datus-semantic-metricflow
Version: 0.1.2
Summary: MetricFlow adapter for Datus semantic layer
Author: Datus Team
Requires-Python: >=3.12
Requires-Dist: pydantic>=2.0.0
Requires-Dist: datus-metricflow>=0.1.7
Provides-Extra: dev
Requires-Dist: pytest>=7.0.0; extra == "dev"
Requires-Dist: pytest-asyncio>=0.21.0; extra == "dev"
Requires-Dist: black>=23.0.0; extra == "dev"
Requires-Dist: ruff>=0.1.0; extra == "dev"
